ml_iris_backprop/__init__.py
ml_iris_backprop/text_reader.py
ml_iris_backprop/data/my_code.py
ml_iris_backprop-0.1.dist-info/METADATA
ml_iris_backprop-0.1.dist-info/WHEEL
ml_iris_backprop-0.1.dist-info/top_level.txt
ml_iris_backprop-0.1.dist-info/RECORD
